mdk/__init__.py
mdk/main.py
mdk/utils.py
mdk-5.8.0.dist-info/LICENSE
mdk-5.8.0.dist-info/METADATA
mdk-5.8.0.dist-info/WHEEL
mdk-5.8.0.dist-info/entry_points.txt
mdk-5.8.0.dist-info/top_level.txt
mdk-5.8.0.dist-info/RECORD
