Metadata-Version: 2.1
Name: mdk
Version: 5.8.0
Summary: a docker-compose helper
Home-page: https://matician.com/
Author: Michael Darr
Author-email: mdarr@matician.com
License: MIT
Classifier: Environment :: Console
Classifier: Intended Audience :: Developers
Classifier: License :: OSI Approved :: MIT License
Classifier: Operating System :: OS Independent
Classifier: Programming Language :: Python :: 3
Requires-Python: >=3
License-File: LICENSE
Requires-Dist: Click (>=7)
